{
  "fetched_at_ist": "2026-07-23T11:00:45.498580+05:30",
  "fetched_at_utc": "2026-07-23T05:30:45.498747Z",
  "source": "https://www.moneycontrol.com/indices/fno/view-option-chain/NIFTY/2026-07-28?",
  "spot": null,
  "row_count": 105,
  "rows": [
    {
      "OI": "37310",
      "OI  Change": "-4290",
      "Volume": "325",
      "Chg in LTP": "21.75 (0.76%)",
      "LTP": "2896.75",
      "Strike  Price": 21100.0,
      "LTP.1": 0.9,
      "Chg in LTP.1": "0.05 (5.88%)",
      "Volume.1": "654745",
      "OI  Change.1": "580450",
      "OI.1": 2662205
    },
    {
      "OI": "130",
      "OI  Change": "-",
      "Volume": "-",
      "Chg in LTP": "-",
      "LTP": "2502.7",
      "Strike  Price": 21150.0,
      "LTP.1": 0.8,
      "Chg in LTP.1": "-0.05 (-5.88%)",
      "Volume.1": "358475",
      "OI  Change.1": "104780",
      "OI.1": 123695
    },
    {
      "OI": "195",
      "OI  Change": "-",
      "Volume": "-",
      "Chg in LTP": "-",
      "LTP": "2030.4",
      "Strike  Price": 21200.0,
      "LTP.1": 0.95,
      "Chg in LTP.1": "0.05 (5.56%)",
      "Volume.1": "344825",
      "OI  Change.1": "438295",
      "OI.1": 656630
    },
    {
      "OI": "65",
      "OI  Change": "65",
      "Volume": "-",
      "Chg in LTP": "-",
      "LTP": "2872.95",
      "Strike  Price": 21250.0,
      "LTP.1": 1.0,
      "Chg in LTP.1": "-",
      "Volume.1": "58890",
      "OI  Change.1": "20540",
      "OI.1": 34905
    },
    {
      "OI": "2210",
      "OI  Change": "-2015",
      "Volume": "1170",
      "Chg in LTP": "3.00 (0.11%)",
      "LTP": "2678",
      "Strike  Price": 21300.0,
      "LTP.1": 1.0,
      "Chg in LTP.1": "0.05 (5.26%)",
      "Volume.1": "156195",
      "OI  Change.1": "401765",
      "OI.1": 516490
    },
    {
      "OI": "-",
      "OI  Change": "-",
      "Volume": "-",
      "Chg in LTP": "-",
      "LTP": "-",
      "Strike  Price": 21350.0,
      "LTP.1": 1.15,
      "Chg in LTP.1": "0.05 (4.55%)",
      "Volume.1": "60060",
      "OI  Change.1": "62075",
      "OI.1": 76765
    },
    {
      "OI": "-",
      "OI  Change": "-",
      "Volume": "-",
      "Chg in LTP": "-",
      "LTP": "-",
      "Strike  Price": 21400.0,
      "LTP.1": 1.1,
      "Chg in LTP.1": "0.05 (4.76%)",
      "Volume.1": "312000",
      "OI  Change.1": "191750",
      "OI.1": 240370
    },
    {
      "OI": "-",
      "OI  Change": "-",
      "Volume": "-",
      "Chg in LTP": "-",
      "LTP": "-",
      "Strike  Price": 21450.0,
      "LTP.1": 1.35,
      "Chg in LTP.1": "0.20 (17.39%)",
      "Volume.1": "48230",
      "OI  Change.1": "20215",
      "OI.1": 27690
    },
    {
      "OI": "424775",
      "OI  Change": "-19630",
      "Volume": "7475",
      "Chg in LTP": "5.95 (0.24%)",
      "LTP": "2485.85",
      "Strike  Price": 21500.0,
      "LTP.1": 1.25,
      "Chg in LTP.1": "0.10 (8.70%)",
      "Volume.1": "512005",
      "OI  Change.1": "52585",
      "OI.1": 1847885
    },
    {
      "OI": "-",
      "OI  Change": "-",
      "Volume": "-",
      "Chg in LTP": "-",
      "LTP": "-",
      "Strike  Price": 21550.0,
      "LTP.1": 1.35,
      "Chg in LTP.1": "0.10 (8.00%)",
      "Volume.1": "23140",
      "OI  Change.1": "8255",
      "OI.1": 17030
    },
    {
      "OI": "-",
      "OI  Change": "-",
      "Volume": "-",
      "Chg in LTP": "-",
      "LTP": "-",
      "Strike  Price": 21600.0,
      "LTP.1": 1.35,
      "Chg in LTP.1": "-",
      "Volume.1": "328640",
      "OI  Change.1": "46475",
      "OI.1": 284635
    },
    {
      "OI": "65",
      "OI  Change": "-",
      "Volume": "-",
      "Chg in LTP": "-",
      "LTP": "1938.2",
      "Strike  Price": 21650.0,
      "LTP.1": 1.4,
      "Chg in LTP.1": "0.05 (3.70%)",
      "Volume.1": "23140",
      "OI  Change.1": "10010",
      "OI.1": 17745
    },
    {
      "OI": "-",
      "OI  Change": "-130",
      "Volume": "-",
      "Chg in LTP": "-",
      "LTP": "2305",
      "Strike  Price": 21700.0,
      "LTP.1": 1.4,
      "Chg in LTP.1": "0.05 (3.70%)",
      "Volume.1": "127725",
      "OI  Change.1": "43485",
      "OI.1": 176865
    },
    {
      "OI": "-",
      "OI  Change": "-",
      "Volume": "-",
      "Chg in LTP": "-",
      "LTP": "2437.6",
      "Strike  Price": 21750.0,
      "LTP.1": 1.55,
      "Chg in LTP.1": "0.10 (6.90%)",
      "Volume.1": "52455",
      "OI  Change.1": "24115",
      "OI.1": 40235
    },
    {
      "OI": "130",
      "OI  Change": "-",
      "Volume": "-",
      "Chg in LTP": "-",
      "LTP": "2230",
      "Strike  Price": 21800.0,
      "LTP.1": 1.65,
      "Chg in LTP.1": "0.10 (6.45%)",
      "Volume.1": "431600",
      "OI  Change.1": "201305",
      "OI.1": 999050
    },
    {
      "OI": "65",
      "OI  Change": "-",
      "Volume": "-",
      "Chg in LTP": "-",
      "LTP": "2031.2",
      "Strike  Price": 21850.0,
      "LTP.1": 1.7,
      "Chg in LTP.1": "0.20 (13.33%)",
      "Volume.1": "28275",
      "OI  Change.1": "3770",
      "OI.1": 30680
    },
    {
      "OI": "520",
      "OI  Change": "455",
      "Volume": "-",
      "Chg in LTP": "-",
      "LTP": "2080",
      "Strike  Price": 21900.0,
      "LTP.1": 1.75,
      "Chg in LTP.1": "0.15 (9.38%)",
      "Volume.1": "227045",
      "OI  Change.1": "76245",
      "OI.1": 223015
    },
    {
      "OI": "130",
      "OI  Change": "-",
      "Volume": "-",
      "Chg in LTP": "-",
      "LTP": "1968.9",
      "Strike  Price": 21950.0,
      "LTP.1": 1.7,
      "Chg in LTP.1": "0.10 (6.25%)",
      "Volume.1": "52780",
      "OI  Change.1": "18265",
      "OI.1": 34255
    },
    {
      "OI": "573235",
      "OI  Change": "-54730",
      "Volume": "31265",
      "Chg in LTP": "-2.55 (-0.13%)",
      "LTP": "1986.4",
      "Strike  Price": 22000.0,
      "LTP.1": 1.9,
      "Chg in LTP.1": "0.20 (11.76%)",
      "Volume.1": "1877720",
      "OI  Change.1": "1795105",
      "OI.1": 4571710
    },
    {
      "OI": "65",
      "OI  Change": "-",
      "Volume": "-",
      "Chg in LTP": "-",
      "LTP": "2230",
      "Strike  Price": 22050.0,
      "LTP.1": 1.9,
      "Chg in LTP.1": "0.25 (15.15%)",
      "Volume.1": "35880",
      "OI  Change.1": "9620",
      "OI.1": 51870
    },
    {
      "OI": "130",
      "OI  Change": "-",
      "Volume": "-",
      "Chg in LTP": "-",
      "LTP": "1855.35",
      "Strike  Price": 22100.0,
      "LTP.1": 1.95,
      "Chg in LTP.1": "0.15 (8.33%)",
      "Volume.1": "996970",
      "OI  Change.1": "509990",
      "OI.1": 681265
    },
    {
      "OI": "1560",
      "OI  Change": "1495",
      "Volume": "-",
      "Chg in LTP": "-",
      "LTP": "1902.9",
      "Strike  Price": 22150.0,
      "LTP.1": 1.9,
      "Chg in LTP.1": "0.05 (2.70%)",
      "Volume.1": "120510",
      "OI  Change.1": "11700",
      "OI.1": 45825
    },
    {
      "OI": "1950",
      "OI  Change": "-65",
      "Volume": "-",
      "Chg in LTP": "-",
      "LTP": "1784.55",
      "Strike  Price": 22200.0,
      "LTP.1": 2.1,
      "Chg in LTP.1": "0.35 (20.00%)",
      "Volume.1": "1002365",
      "OI  Change.1": "255060",
      "OI.1": 714675
    },
    {
      "OI": "260",
      "OI  Change": "-130",
      "Volume": "-",
      "Chg in LTP": "-",
      "LTP": "1730",
      "Strike  Price": 22250.0,
      "LTP.1": 2.0,
      "Chg in LTP.1": "0.20 (11.11%)",
      "Volume.1": "210145",
      "OI  Change.1": "-14235",
      "OI.1": 146185
    },
    {
      "OI": "520",
      "OI  Change": "-65",
      "Volume": "-",
      "Chg in LTP": "-",
      "LTP": "1893",
      "Strike  Price": 22300.0,
      "LTP.1": 2.05,
      "Chg in LTP.1": "0.10 (5.13%)",
      "Volume.1": "822445",
      "OI  Change.1": "345085",
      "OI.1": 1022580
    },
    {
      "OI": "260",
      "OI  Change": "-",
      "Volume": "-",
      "Chg in LTP": "-",
      "LTP": "1636.55",
      "Strike  Price": 22350.0,
      "LTP.1": 2.05,
      "Chg in LTP.1": "-",
      "Volume.1": "485095",
      "OI  Change.1": "138190",
      "OI.1": 161135
    },
    {
      "OI": "845",
      "OI  Change": "-",
      "Volume": "-",
      "Chg in LTP": "-",
      "LTP": "1585",
      "Strike  Price": 22400.0,
      "LTP.1": 2.2,
      "Chg in LTP.1": "-",
      "Volume.1": "756405",
      "OI  Change.1": "147095",
      "OI.1": 390585
    },
    {
      "OI": "325",
      "OI  Change": "-",
      "Volume": "-",
      "Chg in LTP": "-",
      "LTP": "1737.95",
      "Strike  Price": 22450.0,
      "LTP.1": 2.35,
      "Chg in LTP.1": "0.05 (2.17%)",
      "Volume.1": "532220",
      "OI  Change.1": "83980",
      "OI.1": 141310
    },
    {
      "OI": "230750",
      "OI  Change": "-60775",
      "Volume": "24830",
      "Chg in LTP": "-12.55 (-0.84%)",
      "LTP": "1479",
      "Strike  Price": 22500.0,
      "LTP.1": 2.4,
      "Chg in LTP.1": "-0.10 (-4.00%)",
      "Volume.1": "5005715",
      "OI  Change.1": "1038310",
      "OI.1": 4087460
    },
    {
      "OI": "260",
      "OI  Change": "-",
      "Volume": "-",
      "Chg in LTP": "-",
      "LTP": "1639.65",
      "Strike  Price": 22550.0,
      "LTP.1": 2.45,
      "Chg in LTP.1": "-0.10 (-3.92%)",
      "Volume.1": "559130",
      "OI  Change.1": "35685",
      "OI.1": 98020
    },
    {
      "OI": "2405",
      "OI  Change": "-",
      "Volume": "-",
      "Chg in LTP": "-",
      "LTP": "1404.2",
      "Strike  Price": 22600.0,
      "LTP.1": 2.5,
      "Chg in LTP.1": "-0.25 (-9.09%)",
      "Volume.1": "2108795",
      "OI  Change.1": "788515",
      "OI.1": 1153295
    },
    {
      "OI": "6565",
      "OI  Change": "6175",
      "Volume": "6500",
      "Chg in LTP": "-31.20 (-2.33%)",
      "LTP": "1305.55",
      "Strike  Price": 22650.0,
      "LTP.1": 2.7,
      "Chg in LTP.1": "-0.30 (-10.00%)",
      "Volume.1": "1459250",
      "OI  Change.1": "798460",
      "OI.1": 879580
    },
    {
      "OI": "5850",
      "OI  Change": "650",
      "Volume": "6825",
      "Chg in LTP": "-7.00 (-0.54%)",
      "LTP": "1285",
      "Strike  Price": 22700.0,
      "LTP.1": 2.75,
      "Chg in LTP.1": "-0.25 (-8.33%)",
      "Volume.1": "2509845",
      "OI  Change.1": "758225",
      "OI.1": 1455610
    },
    {
      "OI": "17420",
      "OI  Change": "14430",
      "Volume": "17095",
      "Chg in LTP": "3.25 (0.27%)",
      "LTP": "1203.65",
      "Strike  Price": 22750.0,
      "LTP.1": 2.85,
      "Chg in LTP.1": "-0.40 (-12.31%)",
      "Volume.1": "884065",
      "OI  Change.1": "119470",
      "OI.1": 319800
    },
    {
      "OI": "39845",
      "OI  Change": "20345",
      "Volume": "26845",
      "Chg in LTP": "-11.25 (-0.96%)",
      "LTP": "1164",
      "Strike  Price": 22800.0,
      "LTP.1": 2.95,
      "Chg in LTP.1": "-0.50 (-14.49%)",
      "Volume.1": "4895735",
      "OI  Change.1": "1931020",
      "OI.1": 3183310
    },
    {
      "OI": "845",
      "OI  Change": "65",
      "Volume": "-",
      "Chg in LTP": "-",
      "LTP": "1154.5",
      "Strike  Price": 22850.0,
      "LTP.1": 3.25,
      "Chg in LTP.1": "-0.60 (-15.58%)",
      "Volume.1": "2195050",
      "OI  Change.1": "759655",
      "OI.1": 1002040
    },
    {
      "OI": "55835",
      "OI  Change": "520",
      "Volume": "2210",
      "Chg in LTP": "-17.20 (-1.56%)",
      "LTP": "1085",
      "Strike  Price": 22900.0,
      "LTP.1": 3.4,
      "Chg in LTP.1": "-0.75 (-18.07%)",
      "Volume.1": "4398810",
      "OI  Change.1": "961675",
      "OI.1": 1815385
    },
    {
      "OI": "1365",
      "OI  Change": "585",
      "Volume": "195",
      "Chg in LTP": "-78.90 (-7.61%)",
      "LTP": "958",
      "Strike  Price": 22950.0,
      "LTP.1": 3.65,
      "Chg in LTP.1": "-0.95 (-20.65%)",
      "Volume.1": "2810405",
      "OI  Change.1": "692510",
      "OI.1": 994305
    },
    {
      "OI": "637650",
      "OI  Change": "24570",
      "Volume": "72410",
      "Chg in LTP": "2.40 (0.24%)",
      "LTP": "991.4",
      "Strike  Price": 23000.0,
      "LTP.1": 4.0,
      "Chg in LTP.1": "-1.25 (-23.81%)",
      "Volume.1": "12197380",
      "OI  Change.1": "5348330",
      "OI.1": 11346140
    },
    {
      "OI": "1755",
      "OI  Change": "715",
      "Volume": "-",
      "Chg in LTP": "-",
      "LTP": "958.35",
      "Strike  Price": 23050.0,
      "LTP.1": 4.3,
      "Chg in LTP.1": "-1.45 (-25.22%)",
      "Volume.1": "2654860",
      "OI  Change.1": "675545",
      "OI.1": 952640
    },
    {
      "OI": "47255",
      "OI  Change": "-130",
      "Volume": "2535",
      "Chg in LTP": "-5.40 (-0.61%)",
      "LTP": "885.15",
      "Strike  Price": 23100.0,
      "LTP.1": 4.6,
      "Chg in LTP.1": "-1.75 (-27.56%)",
      "Volume.1": "6146075",
      "OI  Change.1": "1073930",
      "OI.1": 2545530
    },
    {
      "OI": "2275",
      "OI  Change": "585",
      "Volume": "195",
      "Chg in LTP": "-31.90 (-3.71%)",
      "LTP": "826.8",
      "Strike  Price": 23150.0,
      "LTP.1": 5.1,
      "Chg in LTP.1": "-2.05 (-28.67%)",
      "Volume.1": "3298100",
      "OI  Change.1": "824785",
      "OI.1": 1054625
    },
    {
      "OI": "53235",
      "OI  Change": "-4290",
      "Volume": "3445",
      "Chg in LTP": "4.00 (0.51%)",
      "LTP": "792.6",
      "Strike  Price": 23200.0,
      "LTP.1": 5.6,
      "Chg in LTP.1": "-2.70 (-32.53%)",
      "Volume.1": "7021885",
      "OI  Change.1": "2231515",
      "OI.1": 4165915
    },
    {
      "OI": "3640",
      "OI  Change": "650",
      "Volume": "1625",
      "Chg in LTP": "-4.60 (-0.62%)",
      "LTP": "743.15",
      "Strike  Price": 23250.0,
      "LTP.1": 6.3,
      "Chg in LTP.1": "-3.30 (-34.38%)",
      "Volume.1": "4296500",
      "OI  Change.1": "815295",
      "OI.1": 1083550
    },
    {
      "OI": "93470",
      "OI  Change": "11505",
      "Volume": "72605",
      "Chg in LTP": "-2.55 (-0.37%)",
      "LTP": "692.05",
      "Strike  Price": 23300.0,
      "LTP.1": 7.15,
      "Chg in LTP.1": "-4.10 (-36.44%)",
      "Volume.1": "9381320",
      "OI  Change.1": "3032965",
      "OI.1": 4789720
    },
    {
      "OI": "44005",
      "OI  Change": "-",
      "Volume": "10725",
      "Chg in LTP": "-5.95 (-0.91%)",
      "LTP": "644.8",
      "Strike  Price": 23350.0,
      "LTP.1": 8.55,
      "Chg in LTP.1": "-4.95 (-36.67%)",
      "Volume.1": "5305365",
      "OI  Change.1": "1089985",
      "OI.1": 1673425
    },
    {
      "OI": "85995",
      "OI  Change": "11245",
      "Volume": "60385",
      "Chg in LTP": "-3.15 (-0.52%)",
      "LTP": "599.2",
      "Strike  Price": 23400.0,
      "LTP.1": 10.25,
      "Chg in LTP.1": "-6.25 (-37.88%)",
      "Volume.1": "8190000",
      "OI  Change.1": "1980095",
      "OI.1": 3771885
    },
    {
      "OI": "31785",
      "OI  Change": "23335",
      "Volume": "31915",
      "Chg in LTP": "-3.10 (-0.56%)",
      "LTP": "550.85",
      "Strike  Price": 23450.0,
      "LTP.1": 12.5,
      "Chg in LTP.1": "-7.40 (-37.19%)",
      "Volume.1": "6552065",
      "OI  Change.1": "2088385",
      "OI.1": 2438280
    },
    {
      "OI": "859820",
      "OI  Change": "161460",
      "Volume": "615810",
      "Chg in LTP": "-5.90 (-1.16%)",
      "LTP": "504.3",
      "Strike  Price": 23500.0,
      "LTP.1": 15.9,
      "Chg in LTP.1": "-8.75 (-35.50%)",
      "Volume.1": "18325645",
      "OI  Change.1": "4248985",
      "OI.1": 9549215
    },
    {
      "OI": "39520",
      "OI  Change": "23920",
      "Volume": "104975",
      "Chg in LTP": "-13.15 (-2.82%)",
      "LTP": "452.75",
      "Strike  Price": 23550.0,
      "LTP.1": 19.45,
      "Chg in LTP.1": "-10.50 (-35.06%)",
      "Volume.1": "5849545",
      "OI  Change.1": "1149070",
      "OI.1": 1554280
    },
    {
      "OI": "269880",
      "OI  Change": "108550",
      "Volume": "742365",
      "Chg in LTP": "-11.05 (-2.61%)",
      "LTP": "412",
      "Strike  Price": 23600.0,
      "LTP.1": 24.4,
      "Chg in LTP.1": "-12.35 (-33.61%)",
      "Volume.1": "14577745",
      "OI  Change.1": "2975050",
      "OI.1": 4788745
    },
    {
      "OI": "86970",
      "OI  Change": "72605",
      "Volume": "473395",
      "Chg in LTP": "-13.35 (-3.51%)",
      "LTP": "367.5",
      "Strike  Price": 23650.0,
      "LTP.1": 30.65,
      "Chg in LTP.1": "-14.35 (-31.89%)",
      "Volume.1": "8151520",
      "OI  Change.1": "1469195",
      "OI.1": 1865890
    },
    {
      "OI": "423800",
      "OI  Change": "265070",
      "Volume": "2960165",
      "Chg in LTP": "-13.45 (-3.96%)",
      "LTP": "326",
      "Strike  Price": 23700.0,
      "LTP.1": 38.95,
      "Chg in LTP.1": "-15.90 (-28.99%)",
      "Volume.1": "19320080",
      "OI  Change.1": "3110315",
      "OI.1": 5819970
    },
    {
      "OI": "260650",
      "OI  Change": "234000",
      "Volume": "2202265",
      "Chg in LTP": "-14.95 (-4.96%)",
      "LTP": "286.45",
      "Strike  Price": 23750.0,
      "LTP.1": 48.95,
      "Chg in LTP.1": "-18.25 (-27.16%)",
      "Volume.1": "11361350",
      "OI  Change.1": "1491750",
      "OI.1": 2047175
    },
    {
      "OI": "1655095",
      "OI  Change": "1265875",
      "Volume": "13796705",
      "Chg in LTP": "-17.60 (-6.63%)",
      "LTP": "247.8",
      "Strike  Price": 23800.0,
      "LTP.1": 61.65,
      "Chg in LTP.1": "-19.70 (-24.22%)",
      "Volume.1": "32947135",
      "OI  Change.1": "5124145",
      "OI.1": 8238620
    },
    {
      "OI": "996645",
      "OI  Change": "967590",
      "Volume": "11639615",
      "Chg in LTP": "-19.05 (-8.20%)",
      "LTP": "213.15",
      "Strike  Price": 23850.0,
      "LTP.1": 76.5,
      "Chg in LTP.1": "-21.05 (-21.58%)",
      "Volume.1": "21534435",
      "OI  Change.1": "3105310",
      "OI.1": 3522350
    },
    {
      "OI": "5111470",
      "OI  Change": "4600700",
      "Volume": "53732900",
      "Chg in LTP": "-20.70 (-10.28%)",
      "LTP": "180.75",
      "Strike  Price": 23900.0,
      "LTP.1": 94.65,
      "Chg in LTP.1": "-22.05 (-18.89%)",
      "Volume.1": "61478430",
      "OI  Change.1": "7757750",
      "OI.1": 10339290
    },
    {
      "OI": "4661865",
      "OI  Change": "4591015",
      "Volume": "38691900",
      "Chg in LTP": "-20.40 (-11.88%)",
      "LTP": "151.25",
      "Strike  Price": 23950.0,
      "LTP.1": 115.2,
      "Chg in LTP.1": "-23.95 (-17.21%)",
      "Volume.1": "37402300",
      "OI  Change.1": "5658315",
      "OI.1": 6138405
    },
    {
      "OI": "15089880",
      "OI  Change": "11088480",
      "Volume": "62304125",
      "Chg in LTP": "-21.95 (-14.88%)",
      "LTP": "125.55",
      "Strike  Price": 24000.0,
      "LTP.1": 139.4,
      "Chg in LTP.1": "-22.40 (-13.84%)",
      "Volume.1": "47296795",
      "OI  Change.1": "7065435",
      "OI.1": 13811980
    },
    {
      "OI": "5551650",
      "OI  Change": "5389345",
      "Volume": "21763430",
      "Chg in LTP": "-21.70 (-17.51%)",
      "LTP": "102.25",
      "Strike  Price": 24050.0,
      "LTP.1": 166.65,
      "Chg in LTP.1": "-22.60 (-11.94%)",
      "Volume.1": "7765485",
      "OI  Change.1": "1875575",
      "OI.1": 2378025
    },
    {
      "OI": "9476285",
      "OI  Change": "7590440",
      "Volume": "28287610",
      "Chg in LTP": "-21.00 (-20.26%)",
      "LTP": "82.65",
      "Strike  Price": 24100.0,
      "LTP.1": 197.3,
      "Chg in LTP.1": "-20.85 (-9.56%)",
      "Volume.1": "11701170",
      "OI  Change.1": "1085630",
      "OI.1": 4220905
    },
    {
      "OI": "4873570",
      "OI  Change": "4530890",
      "Volume": "14723540",
      "Chg in LTP": "-19.80 (-23.17%)",
      "LTP": "65.65",
      "Strike  Price": 24150.0,
      "LTP.1": 230.55,
      "Chg in LTP.1": "-18.85 (-7.56%)",
      "Volume.1": "2012985",
      "OI  Change.1": "-6175",
      "OI.1": 788710
    },
    {
      "OI": "14366235",
      "OI  Change": "9970350",
      "Volume": "31465590",
      "Chg in LTP": "-17.80 (-25.39%)",
      "LTP": "52.3",
      "Strike  Price": 24200.0,
      "LTP.1": 266.95,
      "Chg in LTP.1": "-18.85 (-6.60%)",
      "Volume.1": "7501065",
      "OI  Change.1": "1532375",
      "OI.1": 5956405
    },
    {
      "OI": "3650920",
      "OI  Change": "2466750",
      "Volume": "10622820",
      "Chg in LTP": "-16.35 (-28.58%)",
      "LTP": "40.85",
      "Strike  Price": 24250.0,
      "LTP.1": 305.25,
      "Chg in LTP.1": "-15.80 (-4.92%)",
      "Volume.1": "677040",
      "OI  Change.1": "-171340",
      "OI.1": 769015
    },
    {
      "OI": "8804445",
      "OI  Change": "5187975",
      "Volume": "22081930",
      "Chg in LTP": "-14.80 (-31.90%)",
      "LTP": "31.6",
      "Strike  Price": 24300.0,
      "LTP.1": 347.45,
      "Chg in LTP.1": "-16.60 (-4.56%)",
      "Volume.1": "1946620",
      "OI  Change.1": "-164775",
      "OI.1": 2016040
    },
    {
      "OI": "3052270",
      "OI  Change": "2440360",
      "Volume": "8746855",
      "Chg in LTP": "-12.40 (-33.38%)",
      "LTP": "24.75",
      "Strike  Price": 24350.0,
      "LTP.1": 389.8,
      "Chg in LTP.1": "-11.75 (-2.93%)",
      "Volume.1": "147940",
      "OI  Change.1": "22750",
      "OI.1": 189150
    },
    {
      "OI": "5662605",
      "OI  Change": "3348085",
      "Volume": "14802515",
      "Chg in LTP": "-10.65 (-35.44%)",
      "LTP": "19.4",
      "Strike  Price": 24400.0,
      "LTP.1": 435.4,
      "Chg in LTP.1": "-8.40 (-1.89%)",
      "Volume.1": "490945",
      "OI  Change.1": "-92885",
      "OI.1": 952835
    },
    {
      "OI": "2291770",
      "OI  Change": "1749345",
      "Volume": "8097765",
      "Chg in LTP": "-8.90 (-36.93%)",
      "LTP": "15.2",
      "Strike  Price": 24450.0,
      "LTP.1": 478.85,
      "Chg in LTP.1": "-10.30 (-2.11%)",
      "Volume.1": "51350",
      "OI  Change.1": "-16705",
      "OI.1": 102375
    },
    {
      "OI": "9954360",
      "OI  Change": "4272320",
      "Volume": "18502770",
      "Chg in LTP": "-7.30 (-37.73%)",
      "LTP": "12.05",
      "Strike  Price": 24500.0,
      "LTP.1": 526.9,
      "Chg in LTP.1": "-5.55 (-1.04%)",
      "Volume.1": "753870",
      "OI  Change.1": "65650",
      "OI.1": 2767895
    },
    {
      "OI": "1982045",
      "OI  Change": "1364285",
      "Volume": "6798545",
      "Chg in LTP": "-6.15 (-39.42%)",
      "LTP": "9.45",
      "Strike  Price": 24550.0,
      "LTP.1": 573.05,
      "Chg in LTP.1": "-4.05 (-0.70%)",
      "Volume.1": "17615",
      "OI  Change.1": "24505",
      "OI.1": 95420
    },
    {
      "OI": "5952570",
      "OI  Change": "2941510",
      "Volume": "12252305",
      "Chg in LTP": "-5.10 (-40.16%)",
      "LTP": "7.6",
      "Strike  Price": 24600.0,
      "LTP.1": 624.65,
      "Chg in LTP.1": "-0.45 (-0.07%)",
      "Volume.1": "177190",
      "OI  Change.1": "-67535",
      "OI.1": 429520
    },
    {
      "OI": "2617355",
      "OI  Change": "1851070",
      "Volume": "5150795",
      "Chg in LTP": "-4.15 (-39.71%)",
      "LTP": "6.3",
      "Strike  Price": 24650.0,
      "LTP.1": 677.05,
      "Chg in LTP.1": "3.20 (0.47%)",
      "Volume.1": "2275",
      "OI  Change.1": "26585",
      "OI.1": 40170
    },
    {
      "OI": "6905990",
      "OI  Change": "3831620",
      "Volume": "13915655",
      "Chg in LTP": "-3.20 (-36.78%)",
      "LTP": "5.5",
      "Strike  Price": 24700.0,
      "LTP.1": 720.2,
      "Chg in LTP.1": "1.05 (0.15%)",
      "Volume.1": "80535",
      "OI  Change.1": "14040",
      "OI.1": 261105
    },
    {
      "OI": "1911260",
      "OI  Change": "1226875",
      "Volume": "5363865",
      "Chg in LTP": "-2.80 (-37.33%)",
      "LTP": "4.7",
      "Strike  Price": 24750.0,
      "LTP.1": 775.4,
      "Chg in LTP.1": "6.45 (0.84%)",
      "Volume.1": "5785",
      "OI  Change.1": "15210",
      "OI.1": 33150
    },
    {
      "OI": "5105945",
      "OI  Change": "1237145",
      "Volume": "9156680",
      "Chg in LTP": "-2.35 (-36.72%)",
      "LTP": "4.05",
      "Strike  Price": 24800.0,
      "LTP.1": 815.0,
      "Chg in LTP.1": "-4.95 (-0.60%)",
      "Volume.1": "26390",
      "OI  Change.1": "20865",
      "OI.1": 287755
    },
    {
      "OI": "1502020",
      "OI  Change": "889070",
      "Volume": "4177485",
      "Chg in LTP": "-2.10 (-36.21%)",
      "LTP": "3.7",
      "Strike  Price": 24850.0,
      "LTP.1": 871.8,
      "Chg in LTP.1": "6.60 (0.76%)",
      "Volume.1": "1170",
      "OI  Change.1": "13390",
      "OI.1": 19175
    },
    {
      "OI": "3322410",
      "OI  Change": "1529645",
      "Volume": "7049640",
      "Chg in LTP": "-1.70 (-33.33%)",
      "LTP": "3.4",
      "Strike  Price": 24900.0,
      "LTP.1": 910.0,
      "Chg in LTP.1": "-2.55 (-0.28%)",
      "Volume.1": "2925",
      "OI  Change.1": "19370",
      "OI.1": 82095
    },
    {
      "OI": "3057795",
      "OI  Change": "2497560",
      "Volume": "4841395",
      "Chg in LTP": "-1.60 (-33.68%)",
      "LTP": "3.15",
      "Strike  Price": 24950.0,
      "LTP.1": 973.1,
      "Chg in LTP.1": "14.05 (1.46%)",
      "Volume.1": "455",
      "OI  Change.1": "7800",
      "OI.1": 12415
    },
    {
      "OI": "13377195",
      "OI  Change": "5049720",
      "Volume": "15918630",
      "Chg in LTP": "-1.25 (-29.76%)",
      "LTP": "2.95",
      "Strike  Price": 25000.0,
      "LTP.1": 1021.0,
      "Chg in LTP.1": "4.20 (0.41%)",
      "Volume.1": "294775",
      "OI  Change.1": "-7670",
      "OI.1": 1709630
    },
    {
      "OI": "1204060",
      "OI  Change": "673530",
      "Volume": "2119325",
      "Chg in LTP": "-1.20 (-32.00%)",
      "LTP": "2.55",
      "Strike  Price": 25050.0,
      "LTP.1": 1063.8,
      "Chg in LTP.1": "-0.90 (-0.08%)",
      "Volume.1": "-",
      "OI  Change.1": "195",
      "OI.1": 2210
    },
    {
      "OI": "3683810",
      "OI  Change": "1862185",
      "Volume": "6194175",
      "Chg in LTP": "-1.00 (-30.30%)",
      "LTP": "2.3",
      "Strike  Price": 25100.0,
      "LTP.1": 1119.95,
      "Chg in LTP.1": "11.90 (1.07%)",
      "Volume.1": "2145",
      "OI  Change.1": "2145",
      "OI.1": 49790
    },
    {
      "OI": "1077375",
      "OI  Change": "770185",
      "Volume": "1942980",
      "Chg in LTP": "-0.95 (-30.65%)",
      "LTP": "2.15",
      "Strike  Price": 25150.0,
      "LTP.1": 968.65,
      "Chg in LTP.1": "-",
      "Volume.1": "-",
      "OI  Change.1": "1300",
      "OI.1": 1885
    },
    {
      "OI": "5868720",
      "OI  Change": "3988335",
      "Volume": "6635590",
      "Chg in LTP": "-0.85 (-30.91%)",
      "LTP": "1.9",
      "Strike  Price": 25200.0,
      "LTP.1": 1216.0,
      "Chg in LTP.1": "3.15 (0.26%)",
      "Volume.1": "28665",
      "OI  Change.1": "9620",
      "OI.1": 134485
    },
    {
      "OI": "1008735",
      "OI  Change": "777985",
      "Volume": "1089270",
      "Chg in LTP": "-0.70 (-27.45%)",
      "LTP": "1.85",
      "Strike  Price": 25250.0,
      "LTP.1": 1277.45,
      "Chg in LTP.1": "-",
      "Volume.1": "-",
      "OI  Change.1": "390",
      "OI.1": 1040
    },
    {
      "OI": "5498090",
      "OI  Change": "4252040",
      "Volume": "5680545",
      "Chg in LTP": "-0.60 (-26.67%)",
      "LTP": "1.65",
      "Strike  Price": 25300.0,
      "LTP.1": 1321.0,
      "Chg in LTP.1": "-9.00 (-0.68%)",
      "Volume.1": "455",
      "OI  Change.1": "1560",
      "OI.1": 22295
    },
    {
      "OI": "1944865",
      "OI  Change": "1841710",
      "Volume": "1507935",
      "Chg in LTP": "-0.60 (-26.67%)",
      "LTP": "1.65",
      "Strike  Price": 25350.0,
      "LTP.1": 1180.0,
      "Chg in LTP.1": "-",
      "Volume.1": "-",
      "OI  Change.1": "390",
      "OI.1": 1820
    },
    {
      "OI": "4046315",
      "OI  Change": "2845050",
      "Volume": "5410145",
      "Chg in LTP": "-0.55 (-28.95%)",
      "LTP": "1.35",
      "Strike  Price": 25400.0,
      "LTP.1": 1436.65,
      "Chg in LTP.1": "4.05 (0.28%)",
      "Volume.1": "715",
      "OI  Change.1": "1365",
      "OI.1": 16705
    },
    {
      "OI": "826995",
      "OI  Change": "481195",
      "Volume": "698945",
      "Chg in LTP": "-0.50 (-27.03%)",
      "LTP": "1.35",
      "Strike  Price": 25450.0,
      "LTP.1": 1500.0,
      "Chg in LTP.1": "225.00 (17.65%)",
      "Volume.1": "65",
      "OI  Change.1": "-",
      "OI.1": 195
    },
    {
      "OI": "13558220",
      "OI  Change": "9697155",
      "Volume": "12169690",
      "Chg in LTP": "-0.45 (-24.32%)",
      "LTP": "1.4",
      "Strike  Price": 25500.0,
      "LTP.1": 1520.0,
      "Chg in LTP.1": "-0.95 (-0.06%)",
      "Volume.1": "247195",
      "OI  Change.1": "-81055",
      "OI.1": 1195090
    },
    {
      "OI": "1052285",
      "OI  Change": "605605",
      "Volume": "670085",
      "Chg in LTP": "-0.40 (-24.24%)",
      "LTP": "1.25",
      "Strike  Price": 25550.0,
      "LTP.1": 1208.3,
      "Chg in LTP.1": "-",
      "Volume.1": "-",
      "OI  Change.1": "-",
      "OI.1": 715
    },
    {
      "OI": "2348580",
      "OI  Change": "1214200",
      "Volume": "2055690",
      "Chg in LTP": "-0.45 (-28.12%)",
      "LTP": "1.15",
      "Strike  Price": 25600.0,
      "LTP.1": 1660.0,
      "Chg in LTP.1": "230.00 (16.08%)",
      "Volume.1": "715",
      "OI  Change.1": "-",
      "OI.1": 16770
    },
    {
      "OI": "694460",
      "OI  Change": "243750",
      "Volume": "544830",
      "Chg in LTP": "-0.35 (-23.33%)",
      "LTP": "1.15",
      "Strike  Price": 25650.0,
      "LTP.1": 1485.0,
      "Chg in LTP.1": "-",
      "Volume.1": "-",
      "OI  Change.1": "325",
      "OI.1": 520
    },
    {
      "OI": "1187485",
      "OI  Change": "621920",
      "Volume": "973700",
      "Chg in LTP": "-0.40 (-26.67%)",
      "LTP": "1.1",
      "Strike  Price": 25700.0,
      "LTP.1": 1719.7,
      "Chg in LTP.1": "-0.30 (-0.02%)",
      "Volume.1": "195",
      "OI  Change.1": "130",
      "OI.1": 15405
    },
    {
      "OI": "218075",
      "OI  Change": "56680",
      "Volume": "81770",
      "Chg in LTP": "-0.35 (-25.00%)",
      "LTP": "1.05",
      "Strike  Price": 25750.0,
      "LTP.1": 1735.75,
      "Chg in LTP.1": "-",
      "Volume.1": "-",
      "OI  Change.1": "-",
      "OI.1": 390
    },
    {
      "OI": "1444755",
      "OI  Change": "997165",
      "Volume": "1069575",
      "Chg in LTP": "-0.35 (-26.92%)",
      "LTP": "0.95",
      "Strike  Price": 25800.0,
      "LTP.1": 1840.0,
      "Chg in LTP.1": "25.40 (1.40%)",
      "Volume.1": "130",
      "OI  Change.1": "-325",
      "OI.1": 27040
    },
    {
      "OI": "171340",
      "OI  Change": "27755",
      "Volume": "246610",
      "Chg in LTP": "-0.30 (-22.22%)",
      "LTP": "1.05",
      "Strike  Price": 25850.0,
      "LTP.1": 1660.0,
      "Chg in LTP.1": "-",
      "Volume.1": "-",
      "OI  Change.1": "260",
      "OI.1": 325
    },
    {
      "OI": "496730",
      "OI  Change": "77415",
      "Volume": "556270",
      "Chg in LTP": "-0.40 (-29.63%)",
      "LTP": "0.95",
      "Strike  Price": 25900.0,
      "LTP.1": 1920.0,
      "Chg in LTP.1": "-2.45 (-0.13%)",
      "Volume.1": "780",
      "OI  Change.1": "-520",
      "OI.1": 4485
    },
    {
      "OI": "174460",
      "OI  Change": "46540",
      "Volume": "186225",
      "Chg in LTP": "-0.35 (-28.00%)",
      "LTP": "0.9",
      "Strike  Price": 25950.0,
      "LTP.1": 1990.9,
      "Chg in LTP.1": "-",
      "Volume.1": "-",
      "OI  Change.1": "-195",
      "OI.1": 455
    },
    {
      "OI": "5681455",
      "OI  Change": "1417130",
      "Volume": "2792790",
      "Chg in LTP": "-0.25 (-22.73%)",
      "LTP": "0.85",
      "Strike  Price": 26000.0,
      "LTP.1": 2015.4,
      "Chg in LTP.1": "4.85 (0.24%)",
      "Volume.1": "140660",
      "OI  Change.1": "-225745",
      "OI.1": 1891825
    },
    {
      "OI": "165490",
      "OI  Change": "-1560",
      "Volume": "150605",
      "Chg in LTP": "-0.30 (-26.09%)",
      "LTP": "0.85",
      "Strike  Price": 26050.0,
      "LTP.1": 1980.9,
      "Chg in LTP.1": "-",
      "Volume.1": "-",
      "OI  Change.1": "-",
      "OI.1": 1040
    },
    {
      "OI": "312585",
      "OI  Change": "104195",
      "Volume": "635505",
      "Chg in LTP": "-0.15 (-14.29%)",
      "LTP": "0.9",
      "Strike  Price": 26100.0,
      "LTP.1": 2120.0,
      "Chg in LTP.1": "-",
      "Volume.1": "-",
      "OI  Change.1": "-845",
      "OI.1": 35295
    },
    {
      "OI": "123695",
      "OI  Change": "82680",
      "Volume": "137865",
      "Chg in LTP": "-0.30 (-27.27%)",
      "LTP": "0.8",
      "Strike  Price": 26150.0,
      "LTP.1": 2060.0,
      "Chg in LTP.1": "-",
      "Volume.1": "-",
      "OI  Change.1": "-",
      "OI.1": 65
    },
    {
      "OI": "352885",
      "OI  Change": "230490",
      "Volume": "180375",
      "Chg in LTP": "-0.35 (-31.82%)",
      "LTP": "0.75",
      "Strike  Price": 26200.0,
      "LTP.1": 2218.3,
      "Chg in LTP.1": "-1.70 (-0.08%)",
      "Volume.1": "5460",
      "OI  Change.1": "-2470",
      "OI.1": 42120
    },
    {
      "OI": "196820",
      "OI  Change": "119600",
      "Volume": "169585",
      "Chg in LTP": "-0.20 (-21.05%)",
      "LTP": "0.75",
      "Strike  Price": 26250.0,
      "LTP.1": 1770.65,
      "Chg in LTP.1": "-",
      "Volume.1": "-",
      "OI  Change.1": "-",
      "OI.1": 65
    },
    {
      "OI": "1373775",
      "OI  Change": "635245",
      "Volume": "1204320",
      "Chg in LTP": "-0.20 (-23.53%)",
      "LTP": "0.65",
      "Strike  Price": 26300.0,
      "LTP.1": 2319.05,
      "Chg in LTP.1": "6.85 (0.30%)",
      "Volume.1": "26975",
      "OI  Change.1": "-25220",
      "OI.1": 546520
    }
  ]
}